daaf_plot/__init__.py
daaf_plot/figure/__init__.py
daaf_plot/figure/abstract_figure.py
daaf_plot/figure/abstract_interactive_figure.py
daaf_plot/figure/interactive_lineplot.py
daaf_plot/figure/interactive_pcolormesh.py
daaf_plot/geometry/__init__.py
daaf_plot/geometry/matplotlib_figure_geometry.py
daaf_plot/scale/__init__.py
daaf_plot/scale/linlogp.py
daaf_plot/style/__init__.py
daaf_plot/style/laptop.mplstyle
daaf_plot/style/pcolormesh_hover_formatter.py
daaf_plot/transforms/__init__.py
daaf_plot/transforms/linlogp.py
daaf_plot-1.0.1.dist-info/METADATA
daaf_plot-1.0.1.dist-info/WHEEL
daaf_plot-1.0.1.dist-info/licenses/LICENSE
daaf_plot-1.0.1.dist-info/RECORD
