Metadata-Version: 2.4
Name: daaf-plot
Version: 1.0.1
Summary: Personal python toolbox to make interactive plot in python notebooks
Project-URL: Issues, https://github.com/aFarchi/daaf-plot/issues
Project-URL: Source, https://github.com/aFarchi/daaf-plot
Author-email: Alban Farchi <alban.farchi@ecmwf.int>
License-File: LICENSE
Keywords: interactive plots,notebooks,visualization
Classifier: Framework :: Jupyter :: JupyterLab
Classifier: Framework :: Matplotlib
Classifier: Intended Audience :: Science/Research
Classifier: License :: OSI Approved :: MIT License
Classifier: Operating System :: OS Independent
Classifier: Programming Language :: Python
Classifier: Programming Language :: Python :: 3
Classifier: Programming Language :: Python :: 3 :: Only
Classifier: Topic :: Scientific/Engineering
Classifier: Topic :: Scientific/Engineering :: Visualization
Requires-Python: >=3.11
Requires-Dist: cartopy
Requires-Dist: ipympl
Requires-Dist: ipython
Requires-Dist: ipywidgets
Requires-Dist: matplotlib
Requires-Dist: numpy
Requires-Dist: pandas
Requires-Dist: xarray
Provides-Extra: dev
Requires-Dist: ipykernel; extra == 'dev'
Requires-Dist: netcdf4; extra == 'dev'
Requires-Dist: ruff; extra == 'dev'
